LICENSE
MANIFEST.in
setup.py
django_markdownx3.egg-info/PKG-INFO
django_markdownx3.egg-info/SOURCES.txt
django_markdownx3.egg-info/dependency_links.txt
django_markdownx3.egg-info/requires.txt
django_markdownx3.egg-info/top_level.txt
markdownx/__init__.py
markdownx/admin.py
markdownx/fields.py
markdownx/forms.py
markdownx/models.py
markdownx/settings.py
markdownx/urls.py
markdownx/utils.py
markdownx/views.py
markdownx/widgets.py
markdownx/locale/en/LC_MESSAGES/django.mo
markdownx/locale/en/LC_MESSAGES/django.po
markdownx/locale/pl/LC_MESSAGES/django.mo
markdownx/locale/pl/LC_MESSAGES/django.po
markdownx/static/markdownx/admin/css/markdownx.css
markdownx/static/markdownx/js/markdownx.js
markdownx/templates/markdownx/widget.html