Metadata-Version: 1.1
Name: django-markdownx3
Version: 1.0.2
Summary: Simple markdown editor (without any UI controls) with image uploads (stored in MEDIA_ROOT folder) and live preview
Home-page: https://github.com/pydanny/django-markdownx
Author: adi-
Author-email: aaadeji@gmail.com
License: BSD
Keywords: django markdown live preview images upload
Platform: UNKNOWN
Classifier: Development Status :: 5 - Production/Stable
Classifier: Environment :: Web Environment
Classifier: Framework :: Django
Classifier: Intended Audience :: Developers
Classifier: License :: OSI Approved :: BSD License
Classifier: Topic :: Software Development
Classifier: Topic :: Software Development :: User Interfaces
Classifier: Operating System :: OS Independent
Classifier: Programming Language :: Python :: 2.7
Classifier: Programming Language :: Python :: 3.5
Classifier: Programming Language :: JavaScript
